{"name":"navigateToGooglePage","id":"com.gettingstarted.tests.MyFirstTest:navigateToGooglePage","testCaseName":"com.gettingstarted.tests.MyFirstTest","userStory":{"id":"com.gettingstarted.tests.MyFirstTest","storyName":"My first test","storyClassName":"com.gettingstarted.tests.MyFirstTest","path":"com.gettingstarted.tests","type":"story"},"featureTag":{"name":"Tests/My first test","type":"story","displayName":"Tests/My first test"},"title":"This is my first serenity test method!!!!!","tags":[{"name":"Tests/My first test","type":"story","displayName":"Tests/My first test"}],"startTime":"2020-09-15T19:46:37.761238200-04:00[America/New_York]","duration":28781,"projectKey":"","sessionId":"8dc24d0349817a522f7b4213ba6dd573","driver":"chrome","isManualTestingUpToDate":false,"manual":false,"testSource":"JUnit","result":"SUCCESS"}